<?xml version="1.0" encoding="UTF-8"?>
<!DOCTYPE mapper PUBLIC "-//mybatis.org//DTD Mapper 3.0//EN" "http://mybatis.org/dtd/mybatis-3-mapper.dtd">
<mapper namespace="com.pramy.demo.mybatis.dao.PersonMapper">

  <cache type="com.pramy.demo.mybatis.MyRedisCache"/>
  <resultMap id="BaseResultMap" type="com.pramy.demo.mybatis.po.Person">
    <!--
      WARNING - @mbg.generated
      This element is automatically generated by MyBatis Generator, do not modify.
    -->
    <id column="id" jdbcType="BIGINT" property="id" />
    <result column="address" jdbcType="VARCHAR" property="address" />
    <result column="age" jdbcType="INTEGER" property="age" />
    <result column="name" jdbcType="VARCHAR" property="name" />
  </resultMap>
  <sql id="Base_Column_List">
    <!--
      WARNING - @mbg.generated
      This element is automatically generated by MyBatis Generator, do not modify.
    -->
    id, address, age, name
  </sql>
  <select id="selectByPrimaryKey" parameterType="java.lang.Long" resultMap="BaseResultMap" >
    <!--
      WARNING - @mbg.generated
      This element is automatically generated by MyBatis Generator, do not modify.
    -->
    select 
    <include refid="Base_Column_List" />
    from person
    where id = #{id,jdbcType=BIGINT}
  </select>
  <delete id="deleteByPrimaryKey" parameterType="java.lang.Long" >
    <!--
      WARNING - @mbg.generated
      This element is automatically generated by MyBatis Generator, do not modify.
    -->
    delete from person
    where id = #{id,jdbcType=BIGINT}
  </delete>
  <insert id="insert" parameterType="com.pramy.demo.mybatis.po.Person" useGeneratedKeys="true" keyProperty="id" flushCache="true">
    <!--
      WARNING - @mbg.generated
      This element is automatically generated by MyBatis Generator, do not modify.
    -->
    insert into person (id, address, age, 
      name)
    values (#{id,jdbcType=BIGINT}, #{address,jdbcType=VARCHAR}, #{age,jdbcType=INTEGER}, 
      #{name,jdbcType=VARCHAR})
  </insert>
  <insert id="insertSelective" parameterType="com.pramy.demo.mybatis.po.Person">
    <!--
      WARNING - @mbg.generated
      This element is automatically generated by MyBatis Generator, do not modify.
    -->
    insert into person
    <trim prefix="(" suffix=")" suffixOverrides=",">
      <if test="id != null">
        id,
      </if>
      <if test="address != null">
        address,
      </if>
      <if test="age != null">
        age,
      </if>
      <if test="name != null">
        name,
      </if>
    </trim>
    <trim prefix="values (" suffix=")" suffixOverrides=",">
      <if test="id != null">
        #{id,jdbcType=BIGINT},
      </if>
      <if test="address != null">
        #{address,jdbcType=VARCHAR},
      </if>
      <if test="age != null">
        #{age,jdbcType=INTEGER},
      </if>
      <if test="name != null">
        #{name,jdbcType=VARCHAR},
      </if>
    </trim>
  </insert>
  <update id="updateByPrimaryKeySelective" parameterType="com.pramy.demo.mybatis.po.Person">
    <!--
      WARNING - @mbg.generated
      This element is automatically generated by MyBatis Generator, do not modify.
    -->
    update person
    <set>
      <if test="address != null">
        address = #{address,jdbcType=VARCHAR},
      </if>
      <if test="age != null">
        age = #{age,jdbcType=INTEGER},
      </if>
      <if test="name != null">
        name = #{name,jdbcType=VARCHAR},
      </if>
    </set>
    where id = #{id,jdbcType=BIGINT}
  </update>
  <update id="updateByPrimaryKey" parameterType="com.pramy.demo.mybatis.po.Person">
    <!--
      WARNING - @mbg.generated
      This element is automatically generated by MyBatis Generator, do not modify.
    -->
    update person
    set address = #{address,jdbcType=VARCHAR},
      age = #{age,jdbcType=INTEGER},
      name = #{name,jdbcType=VARCHAR}
    where id = #{id,jdbcType=BIGINT}
  </update>
</mapper>